omop_alchemy/__init__.py
omop_alchemy/config.py
omop_alchemy/errors.py
omop_alchemy/py.typed
omop_alchemy/cdm/__init__.py
omop_alchemy/cdm/base/__init__.py
omop_alchemy/cdm/base/cdm_constants.py
omop_alchemy/cdm/base/cdm_table_base.py
omop_alchemy/cdm/base/column_helpers.py
omop_alchemy/cdm/base/column_mixins.py
omop_alchemy/cdm/base/decorators.py
omop_alchemy/cdm/base/domain_validation.py
omop_alchemy/cdm/base/modifier_interface.py
omop_alchemy/cdm/base/reference_context.py
omop_alchemy/cdm/base/typing.py
omop_alchemy/cdm/model/__init__.py
omop_alchemy/cdm/model/clinical/__init__.py
omop_alchemy/cdm/model/clinical/clinical_event_union.py
omop_alchemy/cdm/model/clinical/condition_occurrence.py
omop_alchemy/cdm/model/clinical/death.py
omop_alchemy/cdm/model/clinical/device_exposure.py
omop_alchemy/cdm/model/clinical/drug_exposure.py
omop_alchemy/cdm/model/clinical/measurement.py
omop_alchemy/cdm/model/clinical/observation.py
omop_alchemy/cdm/model/clinical/person.py
omop_alchemy/cdm/model/clinical/procedure_occurrence.py
omop_alchemy/cdm/model/clinical/specimin.py
omop_alchemy/cdm/model/derived/__init__.py
omop_alchemy/cdm/model/derived/cohort.py
omop_alchemy/cdm/model/derived/cohort_definition.py
omop_alchemy/cdm/model/derived/condition_era.py
omop_alchemy/cdm/model/derived/dose_era.py
omop_alchemy/cdm/model/derived/drug_era.py
omop_alchemy/cdm/model/derived/observation_period.py
omop_alchemy/cdm/model/extended/__init__.py
omop_alchemy/cdm/model/extended/concept_resolver.py
omop_alchemy/cdm/model/extended/event_timeline.py
omop_alchemy/cdm/model/health_economic/__init__.py
omop_alchemy/cdm/model/health_economic/cost.py
omop_alchemy/cdm/model/health_economic/payer_plan_period.py
omop_alchemy/cdm/model/health_system/__init__.py
omop_alchemy/cdm/model/health_system/care_site.py
omop_alchemy/cdm/model/health_system/location.py
omop_alchemy/cdm/model/health_system/provider.py
omop_alchemy/cdm/model/health_system/visit_detail.py
omop_alchemy-0.5.6.dist-info/licenses/LICENSE
omop_alchemy-0.5.6.dist-info/METADATA
omop_alchemy-0.5.6.dist-info/WHEEL
omop_alchemy-0.5.6.dist-info/top_level.txt
omop_alchemy-0.5.6.dist-info/RECORD
