Metadata-Version: 2.4
Name: omop-alchemy
Version: 0.5.6
Summary: SQLAlchemy-based models, validation, and utilities for the OHDSI OMOP Common Data Model
Author-email: Georgie Kennedy <georgie.kennedy@unsw.edu.au>
License: Apache-2.0
Project-URL: Homepage, https://australiancancerdatanetwork.github.io/OMOP_Alchemy/
Project-URL: Repository, https://github.com/AustralianCancerDataNetwork/OMOP_Alchemy
Project-URL: Issues, https://github.com/AustralianCancerDataNetwork/OMOP_Alchemy/issues
Keywords: OMOP,OHDSI,clinical-data,health-informatics,sqlalchemy,ETL,real-world-evidence
Classifier: Development Status :: 4 - Beta
Classifier: Intended Audience :: Science/Research
Classifier: Intended Audience :: Healthcare Industry
Classifier: Topic :: Scientific/Engineering :: Medical Science Apps.
Classifier: License :: OSI Approved :: Apache Software License
Classifier: Programming Language :: Python :: 3
Classifier: Programming Language :: Python :: 3.12
Requires-Python: >=3.12
License-File: LICENSE
Requires-Dist: sqlalchemy>=2.0.45
Requires-Dist: pandas>=2.0
Requires-Dist: pyyaml>=6.0
Requires-Dist: python-dotenv>=1.0
Requires-Dist: orm-loader>=0.3.9
Provides-Extra: dev
Requires-Dist: ipython>=8.0; extra == "dev"
Requires-Dist: pytest>=7.0; extra == "dev"
Requires-Dist: pytest-cov>=4.0; extra == "dev"
Requires-Dist: mypy>=1.8; extra == "dev"
Requires-Dist: ruff>=0.4; extra == "dev"
Requires-Dist: rich>=13.0; extra == "dev"
Requires-Dist: mkdocs-material>=9.7.1; extra == "dev"
Requires-Dist: mkdocstrings-python>=2.0.1; extra == "dev"
Requires-Dist: mkdocs>=1.6.1; extra == "dev"
Requires-Dist: mkdocs-mermaid2-plugin; extra == "dev"
Provides-Extra: docs
Requires-Dist: sphinx; extra == "docs"
Requires-Dist: myst-parser; extra == "docs"
Dynamic: license-file
